{
  "project_info": {
    "project_number": "438624516466",
    "project_id": "sement-shop-mangement",
    "storage_bucket": "sement-shop-mangement.appspot.com"
  },
  "client": [
    {
      "client_info": {
        "mobilesdk_app_id": "1:438624516466:android:bbd9832ebb08ce6ce905eb",
        "android_client_info": {
          "package_name": "com.example.sement_shop_mangement"
        }
      },
      "oauth_client": [
        {
          "client_id": "438624516466-btsvqh8q93iqgsv895v6utakn8e8g3v0.apps.googleusercontent.com",
          "client_type": 3
        }
      ],
      "api_key": [
        {
          "current_key": "AIzaSyBA6BaU9L727pp6qdJAXBDSLpMfpq30T18"
        }
      ],
      "services": {
        "appinvite_service": {
          "other_platform_oauth_client": [
            {
              "client_id": "438624516466-btsvqh8q93iqgsv895v6utakn8e8g3v0.apps.googleusercontent.com",
              "client_type": 3
            }
          ]
        }
      }
    }
  ],
  "configuration_version": "1"
}